{"code": "OGN-067", "card_name": "Blitzcrank, Impassive", "as_of": "2026-06-14", "total_available": 65, "levels": [{"price": 3.0, "qty": 3, "cumulative_qty": 3}, {"price": 3.15, "qty": 1, "cumulative_qty": 4}, {"price": 3.8, "qty": 6, "cumulative_qty": 10}, {"price": 4.0, "qty": 1, "cumulative_qty": 11}, {"price": 4.88, "qty": 2, "cumulative_qty": 13}, {"price": 5.0, "qty": 4, "cumulative_qty": 17}, {"price": 5.74, "qty": 1, "cumulative_qty": 18}, {"price": 5.8, "qty": 4, "cumulative_qty": 22}, {"price": 5.85, "qty": 9, "cumulative_qty": 31}, {"price": 7.8, "qty": 3, "cumulative_qty": 34}, {"price": 8.0, "qty": 9, "cumulative_qty": 43}, {"price": 8.45, "qty": 1, "cumulative_qty": 44}, {"price": 8.8, "qty": 2, "cumulative_qty": 46}, {"price": 8.88, "qty": 10, "cumulative_qty": 56}, {"price": 11.3, "qty": 3, "cumulative_qty": 59}, {"price": 14.8, "qty": 3, "cumulative_qty": 62}, {"price": 15.0, "qty": 1, "cumulative_qty": 63}, {"price": 18.88, "qty": 2, "cumulative_qty": 65}]}