{"code": "OGS-022", "card_name": "Final Spark", "as_of": "2026-06-15", "total_available": 60, "levels": [{"price": 11.72, "qty": 2, "cumulative_qty": 2}, {"price": 11.8, "qty": 4, "cumulative_qty": 6}, {"price": 12.88, "qty": 2, "cumulative_qty": 8}, {"price": 13.5, "qty": 2, "cumulative_qty": 10}, {"price": 13.8, "qty": 9, "cumulative_qty": 19}, {"price": 13.83, "qty": 4, "cumulative_qty": 23}, {"price": 13.85, "qty": 2, "cumulative_qty": 25}, {"price": 14.8, "qty": 3, "cumulative_qty": 28}, {"price": 14.81, "qty": 8, "cumulative_qty": 36}, {"price": 14.85, "qty": 2, "cumulative_qty": 38}, {"price": 15.0, "qty": 2, "cumulative_qty": 40}, {"price": 15.75, "qty": 1, "cumulative_qty": 41}, {"price": 15.85, "qty": 1, "cumulative_qty": 42}, {"price": 17.85, "qty": 4, "cumulative_qty": 46}, {"price": 18.0, "qty": 2, "cumulative_qty": 48}, {"price": 18.71, "qty": 1, "cumulative_qty": 49}, {"price": 20.0, "qty": 1, "cumulative_qty": 50}, {"price": 24.8, "qty": 2, "cumulative_qty": 52}, {"price": 24.88, "qty": 3, "cumulative_qty": 55}, {"price": 25.0, "qty": 2, "cumulative_qty": 57}, {"price": 28.8, "qty": 1, "cumulative_qty": 58}, {"price": 37.88, "qty": 2, "cumulative_qty": 60}]}