{"code": "SFD-022", "card_name": "Long Sword", "as_of": "2026-06-15", "total_available": 206, "levels": [{"price": 0.75, "qty": 3, "cumulative_qty": 3}, {"price": 0.82, "qty": 1, "cumulative_qty": 4}, {"price": 0.88, "qty": 5, "cumulative_qty": 9}, {"price": 1.0, "qty": 4, "cumulative_qty": 13}, {"price": 1.48, "qty": 4, "cumulative_qty": 17}, {"price": 1.5, "qty": 7, "cumulative_qty": 24}, {"price": 1.78, "qty": 4, "cumulative_qty": 28}, {"price": 1.8, "qty": 5, "cumulative_qty": 33}, {"price": 1.88, "qty": 13, "cumulative_qty": 46}, {"price": 2.0, "qty": 20, "cumulative_qty": 66}, {"price": 2.2800000000000002, "qty": 1, "cumulative_qty": 67}, {"price": 2.45, "qty": 11, "cumulative_qty": 78}, {"price": 2.5, "qty": 21, "cumulative_qty": 99}, {"price": 2.75, "qty": 4, "cumulative_qty": 103}, {"price": 2.8, "qty": 34, "cumulative_qty": 137}, {"price": 2.85, "qty": 5, "cumulative_qty": 142}, {"price": 2.88, "qty": 3, "cumulative_qty": 145}, {"price": 3.0, "qty": 23, "cumulative_qty": 168}, {"price": 3.8, "qty": 2, "cumulative_qty": 170}, {"price": 3.88, "qty": 4, "cumulative_qty": 174}, {"price": 4.0, "qty": 3, "cumulative_qty": 177}, {"price": 4.8, "qty": 2, "cumulative_qty": 179}, {"price": 4.88, "qty": 1, "cumulative_qty": 180}, {"price": 5.0, "qty": 9, "cumulative_qty": 189}, {"price": 7.8, "qty": 6, "cumulative_qty": 195}, {"price": 8.8, "qty": 4, "cumulative_qty": 199}, {"price": 14.8, "qty": 6, "cumulative_qty": 205}, {"price": 38.88, "qty": 1, "cumulative_qty": 206}]}