{"code": "SFD-211", "card_name": "Marai Spire", "as_of": "2026-06-15", "total_available": 805, "levels": [{"price": 0.2, "qty": 36, "cumulative_qty": 36}, {"price": 0.23, "qty": 12, "cumulative_qty": 48}, {"price": 0.24, "qty": 3, "cumulative_qty": 51}, {"price": 0.25, "qty": 53, "cumulative_qty": 104}, {"price": 0.28, "qty": 8, "cumulative_qty": 112}, {"price": 0.3, "qty": 80, "cumulative_qty": 192}, {"price": 0.35, "qty": 17, "cumulative_qty": 209}, {"price": 0.38, "qty": 2, "cumulative_qty": 211}, {"price": 0.4, "qty": 4, "cumulative_qty": 215}, {"price": 0.45, "qty": 7, "cumulative_qty": 222}, {"price": 0.48, "qty": 33, "cumulative_qty": 255}, {"price": 0.5, "qty": 101, "cumulative_qty": 356}, {"price": 0.55, "qty": 18, "cumulative_qty": 374}, {"price": 0.7, "qty": 8, "cumulative_qty": 382}, {"price": 0.75, "qty": 81, "cumulative_qty": 463}, {"price": 0.78, "qty": 14, "cumulative_qty": 477}, {"price": 0.8, "qty": 22, "cumulative_qty": 499}, {"price": 0.81, "qty": 3, "cumulative_qty": 502}, {"price": 0.85, "qty": 6, "cumulative_qty": 508}, {"price": 0.88, "qty": 31, "cumulative_qty": 539}, {"price": 1.0, "qty": 86, "cumulative_qty": 625}, {"price": 1.2, "qty": 2, "cumulative_qty": 627}, {"price": 1.25, "qty": 21, "cumulative_qty": 648}, {"price": 1.4, "qty": 7, "cumulative_qty": 655}, {"price": 1.45, "qty": 1, "cumulative_qty": 656}, {"price": 1.48, "qty": 8, "cumulative_qty": 664}, {"price": 1.5, "qty": 15, "cumulative_qty": 679}, {"price": 1.53, "qty": 1, "cumulative_qty": 680}, {"price": 1.75, "qty": 21, "cumulative_qty": 701}, {"price": 1.8, "qty": 13, "cumulative_qty": 714}, {"price": 1.8399999999999999, "qty": 13, "cumulative_qty": 727}, {"price": 1.88, "qty": 32, "cumulative_qty": 759}, {"price": 2.0, "qty": 13, "cumulative_qty": 772}, {"price": 2.75, "qty": 2, "cumulative_qty": 774}, {"price": 2.8, "qty": 3, "cumulative_qty": 777}, {"price": 2.85, "qty": 3, "cumulative_qty": 780}, {"price": 3.0, "qty": 4, "cumulative_qty": 784}, {"price": 3.5, "qty": 2, "cumulative_qty": 786}, {"price": 3.8, "qty": 2, "cumulative_qty": 788}, {"price": 4.5, "qty": 1, "cumulative_qty": 789}, {"price": 4.75, "qty": 3, "cumulative_qty": 792}, {"price": 4.8, "qty": 8, "cumulative_qty": 800}, {"price": 4.88, "qty": 4, "cumulative_qty": 804}, {"price": 8.84, "qty": 1, "cumulative_qty": 805}]}