{"code": "SFD-072", "card_name": "Dropboarder", "as_of": "2026-06-15", "total_available": 734, "levels": [{"price": 0.18, "qty": 12, "cumulative_qty": 12}, {"price": 0.24, "qty": 2, "cumulative_qty": 14}, {"price": 0.25, "qty": 52, "cumulative_qty": 66}, {"price": 0.28, "qty": 4, "cumulative_qty": 70}, {"price": 0.3, "qty": 42, "cumulative_qty": 112}, {"price": 0.31, "qty": 1, "cumulative_qty": 113}, {"price": 0.35, "qty": 3, "cumulative_qty": 116}, {"price": 0.37, "qty": 1, "cumulative_qty": 117}, {"price": 0.38, "qty": 5, "cumulative_qty": 122}, {"price": 0.4, "qty": 27, "cumulative_qty": 149}, {"price": 0.44, "qty": 5, "cumulative_qty": 154}, {"price": 0.45, "qty": 6, "cumulative_qty": 160}, {"price": 0.47, "qty": 2, "cumulative_qty": 162}, {"price": 0.48, "qty": 35, "cumulative_qty": 197}, {"price": 0.5, "qty": 68, "cumulative_qty": 265}, {"price": 0.55, "qty": 22, "cumulative_qty": 287}, {"price": 0.7, "qty": 24, "cumulative_qty": 311}, {"price": 0.75, "qty": 100, "cumulative_qty": 411}, {"price": 0.77, "qty": 2, "cumulative_qty": 413}, {"price": 0.78, "qty": 13, "cumulative_qty": 426}, {"price": 0.8, "qty": 23, "cumulative_qty": 449}, {"price": 0.83, "qty": 3, "cumulative_qty": 452}, {"price": 0.85, "qty": 17, "cumulative_qty": 469}, {"price": 0.88, "qty": 54, "cumulative_qty": 523}, {"price": 1.0, "qty": 78, "cumulative_qty": 601}, {"price": 1.25, "qty": 9, "cumulative_qty": 610}, {"price": 1.48, "qty": 5, "cumulative_qty": 615}, {"price": 1.5, "qty": 19, "cumulative_qty": 634}, {"price": 1.55, "qty": 1, "cumulative_qty": 635}, {"price": 1.8, "qty": 30, "cumulative_qty": 665}, {"price": 1.8399999999999999, "qty": 14, "cumulative_qty": 679}, {"price": 1.85, "qty": 3, "cumulative_qty": 682}, {"price": 1.88, "qty": 17, "cumulative_qty": 699}, {"price": 2.0, "qty": 9, "cumulative_qty": 708}, {"price": 2.11, "qty": 1, "cumulative_qty": 709}, {"price": 2.4, "qty": 2, "cumulative_qty": 711}, {"price": 2.48, "qty": 2, "cumulative_qty": 713}, {"price": 2.75, "qty": 2, "cumulative_qty": 715}, {"price": 2.8, "qty": 2, "cumulative_qty": 717}, {"price": 2.84, "qty": 2, "cumulative_qty": 719}, {"price": 2.88, "qty": 1, "cumulative_qty": 720}, {"price": 3.0, "qty": 6, "cumulative_qty": 726}, {"price": 3.4, "qty": 1, "cumulative_qty": 727}, {"price": 3.88, "qty": 4, "cumulative_qty": 731}, {"price": 5.0, "qty": 1, "cumulative_qty": 732}, {"price": 8.0, "qty": 2, "cumulative_qty": 734}]}