{"code": "UNL-109", "card_name": "Blood Rose", "as_of": "2026-06-15", "total_available": 497, "levels": [{"price": 0.51, "qty": 3, "cumulative_qty": 3}, {"price": 0.52, "qty": 16, "cumulative_qty": 19}, {"price": 0.53, "qty": 2, "cumulative_qty": 21}, {"price": 0.58, "qty": 3, "cumulative_qty": 24}, {"price": 0.8, "qty": 2, "cumulative_qty": 26}, {"price": 0.88, "qty": 10, "cumulative_qty": 36}, {"price": 1.0, "qty": 42, "cumulative_qty": 78}, {"price": 1.15, "qty": 6, "cumulative_qty": 84}, {"price": 1.2, "qty": 3, "cumulative_qty": 87}, {"price": 1.21, "qty": 2, "cumulative_qty": 89}, {"price": 1.25, "qty": 10, "cumulative_qty": 99}, {"price": 1.3, "qty": 1, "cumulative_qty": 100}, {"price": 1.34, "qty": 1, "cumulative_qty": 101}, {"price": 1.48, "qty": 8, "cumulative_qty": 109}, {"price": 1.5, "qty": 20, "cumulative_qty": 129}, {"price": 1.8, "qty": 44, "cumulative_qty": 173}, {"price": 1.85, "qty": 4, "cumulative_qty": 177}, {"price": 2.0, "qty": 35, "cumulative_qty": 212}, {"price": 2.4, "qty": 12, "cumulative_qty": 224}, {"price": 2.45, "qty": 12, "cumulative_qty": 236}, {"price": 2.48, "qty": 2, "cumulative_qty": 238}, {"price": 2.5, "qty": 19, "cumulative_qty": 257}, {"price": 2.58, "qty": 8, "cumulative_qty": 265}, {"price": 2.8, "qty": 99, "cumulative_qty": 364}, {"price": 2.88, "qty": 20, "cumulative_qty": 384}, {"price": 3.0, "qty": 40, "cumulative_qty": 424}, {"price": 3.8, "qty": 12, "cumulative_qty": 436}, {"price": 3.88, "qty": 5, "cumulative_qty": 441}, {"price": 4.0, "qty": 6, "cumulative_qty": 447}, {"price": 4.8, "qty": 30, "cumulative_qty": 477}, {"price": 4.84, "qty": 0, "cumulative_qty": 477}, {"price": 4.88, "qty": 16, "cumulative_qty": 493}, {"price": 5.0, "qty": 4, "cumulative_qty": 497}, {"price": 5.05, "qty": 0, "cumulative_qty": 497}]}