{"code": "UNL-018", "card_name": "Yeti Brawler", "as_of": "2026-06-15", "total_available": 535, "levels": [{"price": 0.22, "qty": 18, "cumulative_qty": 18}, {"price": 0.25, "qty": 10, "cumulative_qty": 28}, {"price": 0.28, "qty": 17, "cumulative_qty": 45}, {"price": 0.3, "qty": 2, "cumulative_qty": 47}, {"price": 0.35, "qty": 1, "cumulative_qty": 48}, {"price": 0.4, "qty": 12, "cumulative_qty": 60}, {"price": 0.42, "qty": 2, "cumulative_qty": 62}, {"price": 0.44, "qty": 7, "cumulative_qty": 69}, {"price": 0.45, "qty": 4, "cumulative_qty": 73}, {"price": 0.48, "qty": 5, "cumulative_qty": 78}, {"price": 0.5, "qty": 36, "cumulative_qty": 114}, {"price": 0.75, "qty": 9, "cumulative_qty": 123}, {"price": 0.78, "qty": 14, "cumulative_qty": 137}, {"price": 0.85, "qty": 4, "cumulative_qty": 141}, {"price": 0.88, "qty": 51, "cumulative_qty": 192}, {"price": 1.0, "qty": 57, "cumulative_qty": 249}, {"price": 1.18, "qty": 4, "cumulative_qty": 253}, {"price": 1.2, "qty": 11, "cumulative_qty": 264}, {"price": 1.25, "qty": 17, "cumulative_qty": 281}, {"price": 1.28, "qty": 3, "cumulative_qty": 284}, {"price": 1.38, "qty": 6, "cumulative_qty": 290}, {"price": 1.4, "qty": 11, "cumulative_qty": 301}, {"price": 1.41, "qty": 10, "cumulative_qty": 311}, {"price": 1.45, "qty": 2, "cumulative_qty": 313}, {"price": 1.48, "qty": 37, "cumulative_qty": 350}, {"price": 1.5, "qty": 67, "cumulative_qty": 417}, {"price": 1.75, "qty": 18, "cumulative_qty": 435}, {"price": 1.8, "qty": 10, "cumulative_qty": 445}, {"price": 1.8399999999999999, "qty": 11, "cumulative_qty": 456}, {"price": 1.88, "qty": 2, "cumulative_qty": 458}, {"price": 2.0, "qty": 40, "cumulative_qty": 498}, {"price": 2.2800000000000002, "qty": 1, "cumulative_qty": 499}, {"price": 2.5, "qty": 13, "cumulative_qty": 512}, {"price": 2.58, "qty": 2, "cumulative_qty": 514}, {"price": 2.8, "qty": 8, "cumulative_qty": 522}, {"price": 2.88, "qty": 1, "cumulative_qty": 523}, {"price": 3.0, "qty": 3, "cumulative_qty": 526}, {"price": 3.5, "qty": 3, "cumulative_qty": 529}, {"price": 3.88, "qty": 2, "cumulative_qty": 531}, {"price": 4.5, "qty": 1, "cumulative_qty": 532}, {"price": 18.8, "qty": 3, "cumulative_qty": 535}]}