{"code": "UNL-079", "card_name": "Diana, Lunari", "as_of": "2026-06-15", "total_available": 520, "levels": [{"price": 0.88, "qty": 8, "cumulative_qty": 8}, {"price": 1.0, "qty": 1, "cumulative_qty": 9}, {"price": 1.25, "qty": 4, "cumulative_qty": 13}, {"price": 1.3, "qty": 1, "cumulative_qty": 14}, {"price": 1.35, "qty": 41, "cumulative_qty": 55}, {"price": 1.4, "qty": 11, "cumulative_qty": 66}, {"price": 1.5, "qty": 24, "cumulative_qty": 90}, {"price": 1.8, "qty": 28, "cumulative_qty": 118}, {"price": 1.85, "qty": 1, "cumulative_qty": 119}, {"price": 1.88, "qty": 34, "cumulative_qty": 153}, {"price": 2.0, "qty": 49, "cumulative_qty": 202}, {"price": 2.7800000000000002, "qty": 1, "cumulative_qty": 203}, {"price": 2.8, "qty": 10, "cumulative_qty": 213}, {"price": 2.85, "qty": 5, "cumulative_qty": 218}, {"price": 2.88, "qty": 23, "cumulative_qty": 241}, {"price": 3.0, "qty": 45, "cumulative_qty": 286}, {"price": 3.23, "qty": 7, "cumulative_qty": 293}, {"price": 3.45, "qty": 21, "cumulative_qty": 314}, {"price": 3.48, "qty": 6, "cumulative_qty": 320}, {"price": 3.5, "qty": 12, "cumulative_qty": 332}, {"price": 3.8, "qty": 65, "cumulative_qty": 397}, {"price": 3.85, "qty": 5, "cumulative_qty": 402}, {"price": 3.88, "qty": 14, "cumulative_qty": 416}, {"price": 4.0, "qty": 12, "cumulative_qty": 428}, {"price": 4.25, "qty": 1, "cumulative_qty": 429}, {"price": 4.8, "qty": 7, "cumulative_qty": 436}, {"price": 4.84, "qty": 12, "cumulative_qty": 448}, {"price": 4.88, "qty": 24, "cumulative_qty": 472}, {"price": 5.0, "qty": 6, "cumulative_qty": 478}, {"price": 5.8, "qty": 20, "cumulative_qty": 498}, {"price": 7.35, "qty": 11, "cumulative_qty": 509}, {"price": 8.8, "qty": 11, "cumulative_qty": 520}]}