{"code": "UNL-167", "card_name": "Starhound", "as_of": "2026-06-15", "total_available": 461, "levels": [{"price": 0.28, "qty": 12, "cumulative_qty": 12}, {"price": 0.3, "qty": 4, "cumulative_qty": 16}, {"price": 0.31, "qty": 3, "cumulative_qty": 19}, {"price": 0.41, "qty": 8, "cumulative_qty": 27}, {"price": 0.45, "qty": 4, "cumulative_qty": 31}, {"price": 0.5, "qty": 48, "cumulative_qty": 79}, {"price": 0.53, "qty": 1, "cumulative_qty": 80}, {"price": 0.78, "qty": 35, "cumulative_qty": 115}, {"price": 0.83, "qty": 2, "cumulative_qty": 117}, {"price": 0.85, "qty": 6, "cumulative_qty": 123}, {"price": 0.88, "qty": 19, "cumulative_qty": 142}, {"price": 1.0, "qty": 23, "cumulative_qty": 165}, {"price": 1.2, "qty": 7, "cumulative_qty": 172}, {"price": 1.25, "qty": 12, "cumulative_qty": 184}, {"price": 1.28, "qty": 19, "cumulative_qty": 203}, {"price": 1.3, "qty": 15, "cumulative_qty": 218}, {"price": 1.34, "qty": 2, "cumulative_qty": 220}, {"price": 1.38, "qty": 8, "cumulative_qty": 228}, {"price": 1.4, "qty": 13, "cumulative_qty": 241}, {"price": 1.48, "qty": 29, "cumulative_qty": 270}, {"price": 1.5, "qty": 65, "cumulative_qty": 335}, {"price": 1.75, "qty": 18, "cumulative_qty": 353}, {"price": 1.8, "qty": 10, "cumulative_qty": 363}, {"price": 1.8399999999999999, "qty": 11, "cumulative_qty": 374}, {"price": 1.88, "qty": 1, "cumulative_qty": 375}, {"price": 2.0, "qty": 45, "cumulative_qty": 420}, {"price": 2.5, "qty": 10, "cumulative_qty": 430}, {"price": 2.8, "qty": 2, "cumulative_qty": 432}, {"price": 2.85, "qty": 2, "cumulative_qty": 434}, {"price": 2.88, "qty": 2, "cumulative_qty": 436}, {"price": 3.0, "qty": 16, "cumulative_qty": 452}, {"price": 3.48, "qty": 1, "cumulative_qty": 453}, {"price": 3.75, "qty": 3, "cumulative_qty": 456}, {"price": 3.88, "qty": 2, "cumulative_qty": 458}, {"price": 4.8, "qty": 2, "cumulative_qty": 460}, {"price": 4.84, "qty": 1, "cumulative_qty": 461}]}